easyaiogram/__init__.py
easyaiogram/main.py
easyaiogram-0.1.0.dist-info/METADATA
easyaiogram-0.1.0.dist-info/WHEEL
easyaiogram-0.1.0.dist-info/top_level.txt
easyaiogram-0.1.0.dist-info/RECORD
