Metadata-Version: 2.4
Name: easyaiogram
Version: 0.1.0
Summary: The library based on making telegram bots and simple version of aigram.
Author-email: Bobojon <pubgmbobojon@gmail.com>
License: MIT
Project-URL: Homepage, https://instagram.com/bbbv_vv11
Project-URL: Issues, https://github.com/bobojonabdurahmonov
Requires-Python: >=3.7
